static_stig/stig_runner.py
static_stig-0.1.10.dist-info/METADATA
static_stig-0.1.10.dist-info/WHEEL
static_stig-0.1.10.dist-info/entry_points.txt
static_stig-0.1.10.dist-info/top_level.txt
static_stig-0.1.10.dist-info/RECORD
