Metadata-Version: 2.1
Name: static-stig
Version: 0.1.10
